classification_model/VERSION
classification_model/__init__.py
classification_model/config.yml
classification_model/pipeline.py
classification_model/predict.py
classification_model/train_pipeline.py
classification_model/config/__init__.py
classification_model/config/core.py
classification_model/datasets/sample_train_data.csv
classification_model/datasets/test.csv
classification_model/processing/__init__.py
classification_model/processing/data_manager.py
classification_model/processing/preprocess.py
classification_model/processing/validate.py
classification_model/trained_models/classification_model_output_v0.2.0.joblib
lcd_classification_model-0.2.0.dist-info/METADATA
lcd_classification_model-0.2.0.dist-info/WHEEL
lcd_classification_model-0.2.0.dist-info/top_level.txt
lcd_classification_model-0.2.0.dist-info/RECORD
